lsbs/__init__.py
lsbs-0.0.1.dist-info/METADATA
lsbs-0.0.1.dist-info/WHEEL
lsbs-0.0.1.dist-info/top_level.txt
lsbs-0.0.1.dist-info/RECORD
