Metadata-Version: 2.1
Name: lsbs
Version: 0.0.1
Summary: Least Significat Bit (LSB) Steganography
Home-page: UNKNOWN
Author: N3XU5_666
Author-email: <n3xu5.evil.666@gmail.com>
License: UNKNOWN
Keywords: python,image,audio,steganography
Platform: UNKNOWN
Classifier: Development Status :: 2 - Pre-Alpha
Classifier: Intended Audience :: Developers
Classifier: Programming Language :: Python :: 3
Classifier: Operating System :: Unix
Classifier: Operating System :: MacOS :: MacOS X
Classifier: Operating System :: Microsoft :: Windows
Requires-Dist: Pillow
Requires-Dist: numpy
Requires-Dist: pydub
